Workbook

Sheet Dashboard
A1: RESALE BUSINESS MANAGEMENT HUBS
B3: TOTAL REVENUE | D3: NET PROFIT | F3: CASH TIED IN STOCK | H3: AVG DAYS TO SELL | J3: ACTIVE INVENTORY VALUE
B4: =SUM('Sales Log'!B:B) | D4: =SUM('Sales Log'!H:H) | F4: =SUMIFS(Inventory!E:E, Inventory!G:G, "Active") | H4: =AVERAGE('Sales Log'!I:I) | J4: =COUNTIFS(Inventory!G:G, "Active")
B7: Top Performance Categories | F7: Supplier ROI Standings
B8: =SORT('Category Performance'!A2:D20, 3, -1) | F8: =SORT('Suppliers & COGS Tracking'!A2:D20, 4, -1)

Sheet Inventory
A1: SKU | B1: Brand | C1: Category | D1: Size | E1: COGS | F1: Supplier | G1: Status | H1: Date Listed

Sheet Sales Log
A1: SKU | B1: Sale Price | C1: Platform | D1: Date Sold | E1: COGS (Auto) | F1: Platform Fee (Auto) | G1: Postage (Auto) | H1: Net Profit (Auto) | I1: Days to Sell (Auto)
E2: =IF(ISBLANK(A2), "", XLOOKUP(A2, Inventory!A:A, Inventory!E:E, 0)) | F2: =IF(ISBLANK(A2), "", (B2 * XLOOKUP(C2, 'Fees & Postage Table'!A:A, 'Fees & Postage Table'!C:C, 0)) + XLOOKUP(C2, 'Fees & Postage Table'!A:A, 'Fees & Postage Table'!B:B, 0)) | G2: =IF(ISBLANK(A2), "", XLOOKUP(C2, 'Fees & Postage Table'!A:A, 'Fees & Postage Table'!D:D, 0)) | H2: =IF(ISBLANK(A2), "", B2 - E2 - F2 - G2) | I2: =IF(ISBLANK(A2), "", D2 - XLOOKUP(A2, Inventory!A:A, Inventory!H:H, TODAY()))
E3: =IF(ISBLANK(A3), "", XLOOKUP(A3, Inventory!A:A, Inventory!E:E, 0)) | F3: =IF(ISBLANK(A3), "", (B3 * XLOOKUP(C3, 'Fees & Postage Table'!A:A, 'Fees & Postage Table'!C:C, 0)) + XLOOKUP(C3, 'Fees & Postage Table'!A:A, 'Fees & Postage Table'!B:B, 0)) | G3: =IF(ISBLANK(A3), "", XLOOKUP(C3, 'Fees & Postage Table'!A:A, 'Fees & Postage Table'!D:D, 0)) | H3: =IF(ISBLANK(A3), "", B3 - E3 - F3 - G3) | I3: =IF(ISBLANK(A3), "", D3 - XLOOKUP(A3, Inventory!A:A, Inventory!H:H, TODAY()))
E4: =IF(ISBLANK(A4), "", XLOOKUP(A4, Inventory!A:A, Inventory!E:E, 0)) | F4: =IF(ISBLANK(A4), "", (B4 * XLOOKUP(C4, 'Fees & Postage Table'!A:A, 'Fees & Postage Table'!C:C, 0)) + XLOOKUP(C4, 'Fees & Postage Table'!A:A, 'Fees & Postage Table'!B:B, 0)) | G4: =IF(ISBLANK(A4), "", XLOOKUP(C4, 'Fees & Postage Table'!A:A, 'Fees & Postage Table'!D:D, 0)) | H4: =IF(ISBLANK(A4), "", B4 - E4 - F4 - G4) | I4: =IF(ISBLANK(A4), "", D4 - XLOOKUP(A4, Inventory!A:A, Inventory!H:H, TODAY()))
E5: =IF(ISBLANK(A5), "", XLOOKUP(A5, Inventory!A:A, Inventory!E:E, 0)) | F5: =IF(ISBLANK(A5), "", (B5 * XLOOKUP(C5, 'Fees & Postage Table'!A:A, 'Fees & Postage Table'!C:C, 0)) + XLOOKUP(C5, 'Fees & Postage Table'!A:A, 'Fees & Postage Table'!B:B, 0)) | G5: =IF(ISBLANK(A5), "", XLOOKUP(C5, 'Fees & Postage Table'!A:A, 'Fees & Postage Table'!D:D, 0)) | H5: =IF(ISBLANK(A5), "", B5 - E5 - F5 - G5) | I5: =IF(ISBLANK(A5), "", D5 - XLOOKUP(A5, Inventory!A:A, Inventory!H:H, TODAY()))
E6: =IF(ISBLANK(A6), "", XLOOKUP(A6, Inventory!A:A, Inventory!E:E, 0)) | F6: =IF(ISBLANK(A6), "", (B6 * XLOOKUP(C6, 'Fees & Postage Table'!A:A, 'Fees & Postage Table'!C:C, 0)) + XLOOKUP(C6, 'Fees & Postage Table'!A:A, 'Fees & Postage Table'!B:B, 0)) | G6: =IF(ISBLANK(A6), "", XLOOKUP(C6, 'Fees & Postage Table'!A:A, 'Fees & Postage Table'!D:D, 0)) | H6: =IF(ISBLANK(A6), "", B6 - E6 - F6 - G6) | I6: =IF(ISBLANK(A6), "", D6 - XLOOKUP(A6, Inventory!A:A, Inventory!H:H, TODAY()))
E7: =IF(ISBLANK(A7), "", XLOOKUP(A7, Inventory!A:A, Inventory!E:E, 0)) | F7: =IF(ISBLANK(A7), "", (B7 * XLOOKUP(C7, 'Fees & Postage Table'!A:A, 'Fees & Postage Table'!C:C, 0)) + XLOOKUP(C7, 'Fees & Postage Table'!A:A, 'Fees & Postage Table'!B:B, 0)) | G7: =IF(ISBLANK(A7), "", XLOOKUP(C7, 'Fees & Postage Table'!A:A, 'Fees & Postage Table'!D:D, 0)) | H7: =IF(ISBLANK(A7), "", B7 - E7 - F7 - G7) | I7: =IF(ISBLANK(A7), "", D7 - XLOOKUP(A7, Inventory!A:A, Inventory!H:H, TODAY()))
E8: =IF(ISBLANK(A8), "", XLOOKUP(A8, Inventory!A:A, Inventory!E:E, 0)) | F8: =IF(ISBLANK(A8), "", (B8 * XLOOKUP(C8, 'Fees & Postage Table'!A:A, 'Fees & Postage Table'!C:C, 0)) + XLOOKUP(C8, 'Fees & Postage Table'!A:A, 'Fees & Postage Table'!B:B, 0)) | G8: =IF(ISBLANK(A8), "", XLOOKUP(C8, 'Fees & Postage Table'!A:A, 'Fees & Postage Table'!D:D, 0)) | H8: =IF(ISBLANK(A8), "", B8 - E8 - F8 - G8) | I8: =IF(ISBLANK(A8), "", D8 - XLOOKUP(A8, Inventory!A:A, Inventory!H:H, TODAY()))
E9: =IF(ISBLANK(A9), "", XLOOKUP(A9, Inventory!A:A, Inventory!E:E, 0)) | F9: =IF(ISBLANK(A9), "", (B9 * XLOOKUP(C9, 'Fees & Postage Table'!A:A, 'Fees & Postage Table'!C:C, 0)) + XLOOKUP(C9, 'Fees & Postage Table'!A:A, 'Fees & Postage Table'!B:B, 0)) | G9: =IF(ISBLANK(A9), "", XLOOKUP(C9, 'Fees & Postage Table'!A:A, 'Fees & Postage Table'!D:D, 0)) | H9: =IF(ISBLANK(A9), "", B9 - E9 - F9 - G9) | I9: =IF(ISBLANK(A9), "", D9 - XLOOKUP(A9, Inventory!A:A, Inventory!H:H, TODAY()))
E10: =IF(ISBLANK(A10), "", XLOOKUP(A10, Inventory!A:A, Inventory!E:E, 0)) | F10: =IF(ISBLANK(A10), "", (B10 * XLOOKUP(C10, 'Fees & Postage Table'!A:A, 'Fees & Postage Table'!C:C, 0)) + XLOOKUP(C10, 'Fees & Postage Table'!A:A, 'Fees & Postage Table'!B:B, 0)) | G10: =IF(ISBLANK(A10), "", XLOOKUP(C10, 'Fees & Postage Table'!A:A, 'Fees & Postage Table'!D:D, 0)) | H10: =IF(ISBLANK(A10), "", B10 - E10 - F10 - G10) | I10: =IF(ISBLANK(A10), "", D10 - XLOOKUP(A10, Inventory!A:A, Inventory!H:H, TODAY()))
E11: =IF(ISBLANK(A11), "", XLOOKUP(A11, Inventory!A:A, Inventory!E:E, 0)) | F11: =IF(ISBLANK(A11), "", (B11 * XLOOKUP(C11, 'Fees & Postage Table'!A:A, 'Fees & Postage Table'!C:C, 0)) + XLOOKUP(C11, 'Fees & Postage Table'!A:A, 'Fees & Postage Table'!B:B, 0)) | G11: =IF(ISBLANK(A11), "", XLOOKUP(C11, 'Fees & Postage Table'!A:A, 'Fees & Postage Table'!D:D, 0)) | H11: =IF(ISBLANK(A11), "", B11 - E11 - F11 - G11) | I11: =IF(ISBLANK(A11), "", D11 - XLOOKUP(A11, Inventory!A:A, Inventory!H:H, TODAY()))
E12: =IF(ISBLANK(A12), "", XLOOKUP(A12, Inventory!A:A, Inventory!E:E, 0)) | F12: =IF(ISBLANK(A12), "", (B12 * XLOOKUP(C12, 'Fees & Postage Table'!A:A, 'Fees & Postage Table'!C:C, 0)) + XLOOKUP(C12, 'Fees & Postage Table'!A:A, 'Fees & Postage Table'!B:B, 0)) | G12: =IF(ISBLANK(A12), "", XLOOKUP(C12, 'Fees & Postage Table'!A:A, 'Fees & Postage Table'!D:D, 0)) | H12: =IF(ISBLANK(A12), "", B12 - E12 - F12 - G12) | I12: =IF(ISBLANK(A12), "", D12 - XLOOKUP(A12, Inventory!A:A, Inventory!H:H, TODAY()))
E13: =IF(ISBLANK(A13), "", XLOOKUP(A13, Inventory!A:A, Inventory!E:E, 0)) | F13: =IF(ISBLANK(A13), "", (B13 * XLOOKUP(C13, 'Fees & Postage Table'!A:A, 'Fees & Postage Table'!C:C, 0)) + XLOOKUP(C13, 'Fees & Postage Table'!A:A, 'Fees & Postage Table'!B:B, 0)) | G13: =IF(ISBLANK(A13), "", XLOOKUP(C13, 'Fees & Postage Table'!A:A, 'Fees & Postage Table'!D:D, 0)) | H13: =IF(ISBLANK(A13), "", B13 - E13 - F13 - G13) | I13: =IF(ISBLANK(A13), "", D13 - XLOOKUP(A13, Inventory!A:A, Inventory!H:H, TODAY()))
... E1499: =IF(ISBLANK(A1499), "", XLOOKUP(A1499, Inventory!A:A, Inventory!E:E, 0)) | F1499: =IF(ISBLANK(A1499), "", (B1499 * XLOOKUP(C1499, 'Fees & Postage Table'!A:A, 'Fees & Postage Table'!C:C, 0)) + XLOOKUP(C1499, 'Fees & Postage Table'!A:A, 'Fees & Postage Table'!B:B, 0)) | G1499: =IF(ISBLANK(A1499), "", XLOOKUP(C1499, 'Fees & Postage Table'!A:A, 'Fees & Postage Table'!D:D, 0)) | H1499: =IF(ISBLANK(A1499), "", B1499 - E1499 - F1499 - G1499) | I1499: =IF(ISBLANK(A1499), "", D1499 - XLOOKUP(A1499, Inventory!A:A, Inventory!H:H, TODAY()))

Sheet Fees & Postage Table
A1: Platform | B1: Fixed Fee | C1: Variable Rate | D1: Avg Postage
A2: eBay | B2: 0.3 | C2: 0.128 | D2: 4.5
A3: Vinted | B3: 0 | C3: 0 | D3: 0
A4: Depop | B4: 0 | C4: 0.1 | D4: 4

Sheet Suppliers & COGS Tracking
A1: Supplier | B1: Total Invested | C1: Total Returns | D1: Supplier ROI
A2: =UNIQUE(FILTER(Inventory!F2:F2000, Inventory!F2:F2000<>"")) | B2: =SUMIFS(Inventory!E:E, Inventory!F:F, A2#) | C2: =SUMIFS('Sales Log'!H:H, 'Sales Log'!A:A, XLOOKUP(A2#, Inventory!F:F, Inventory!A:A, "")) | D2: =IF(B2#=0, 0, C2# / B2#)

Sheet SKU Generator
A1: Brand Initials | B1: Category Code | C1: Sequence | D1: Generated SKU
A2: NK | B2: TSH | C2: 1001 | D2: =CONCATENATE(A2, "-", B2, "-", C2)

Sheet Category Performance
A1: Category | B1: Total Revenue | C1: Total Net Profit | D1: Items Sold
A2: =UNIQUE(FILTER(Inventory!C2:C2000, Inventory!C2:C2000<>"")) | B2: =SUMIFS('Sales Log'!B:B, 'Sales Log'!A:A, A2#) | C2: =SUMIFS('Sales Log'!H:H, 'Sales Log'!A:A, A2#) | D2: =COUNTIFS('Sales Log'!A:A, A2#)

Sheet Sell Through Engine
A1: Category | B1: Total Listed | C1: Total Sold | D1: Sell-Through Rate
A2: =UNIQUE(FILTER(Inventory!C2:C2000, Inventory!C2:C2000<>"")) | B2: =COUNTIFS(Inventory!C:C, A2#) | C2: =COUNTIFS('Sales Log'!A:A, XLOOKUP(A2#, Inventory!C:C, Inventory!A:A, "")) | D2: =IF(B2#=0, 0, C2# / B2#)
